pyPoetryDB.py
pyPoetryDB-1.0.0.dist-info/DESCRIPTION.rst
pyPoetryDB-1.0.0.dist-info/METADATA
pyPoetryDB-1.0.0.dist-info/RECORD
pyPoetryDB-1.0.0.dist-info/WHEEL
pyPoetryDB-1.0.0.dist-info/metadata.json
pyPoetryDB-1.0.0.dist-info/top_level.txt
