Metadata-Version: 2.0
Name: pyPoetryDB
Version: 1.0.0
Summary: A simple and easy to use Python 3+ library for fetching data from http://poetrydb.org
Home-page: https://github.com/MatthewCS/PyPoetryDB
Author: Matthew C. S.
Author-email: msprague13@outlook.com
License: UNKNOWN
Platform: UNKNOWN
